BioNAS/__init__.py
BioNAS/tensorflow_mem.py
BioNAS/train.py
BioNAS/Controller/__init__.py
BioNAS/Controller/actor_critic.py
BioNAS/Controller/controller.py
BioNAS/Controller/manager.py
BioNAS/Controller/model.py
BioNAS/Controller/post_processing.py
BioNAS/Controller/reward.py
BioNAS/Controller/state_space.py
BioNAS/Controller/train.py
BioNAS/Interpret/__init__.py
BioNAS/Interpret/interpret.py
BioNAS/Interpret/sequence_model.py
BioNAS/KFunctions/K_func.py
BioNAS/KFunctions/K_math.py
BioNAS/KFunctions/__init__.py
BioNAS/MockBlackBox/__init__.py
BioNAS/MockBlackBox/explore_lambda.py
BioNAS/MockBlackBox/gold_standard.py
BioNAS/MockBlackBox/grid_search.py
BioNAS/MockBlackBox/mock_manager.py
BioNAS/MockBlackBox/simple_conv1d_space.py
BioNAS/MockBlackBox/tmp.py
BioNAS/operators/__init__.py
BioNAS/operators/constraints.py
BioNAS/operators/convolutional.py
BioNAS/operators/custom_filters.py
BioNAS/operators/regularizers.py
BioNAS/operators/sparsek.py
BioNAS/resources/__init__.py
BioNAS/resources/mock_black_box/tmp_1/train_history.csv
BioNAS/resources/mock_black_box/tmp_10/train_history.csv
BioNAS/resources/mock_black_box/tmp_11/train_history.csv
BioNAS/resources/mock_black_box/tmp_12/train_history.csv
BioNAS/resources/mock_black_box/tmp_13/train_history.csv
BioNAS/resources/mock_black_box/tmp_14/train_history.csv
BioNAS/resources/mock_black_box/tmp_15/train_history.csv
BioNAS/resources/mock_black_box/tmp_16/train_history.csv
BioNAS/resources/mock_black_box/tmp_17/train_history.csv
BioNAS/resources/mock_black_box/tmp_18/train_history.csv
BioNAS/resources/mock_black_box/tmp_19/train_history.csv
BioNAS/resources/mock_black_box/tmp_2/train_history.csv
BioNAS/resources/mock_black_box/tmp_20/train_history.csv
BioNAS/resources/mock_black_box/tmp_3/train_history.csv
BioNAS/resources/mock_black_box/tmp_4/train_history.csv
BioNAS/resources/mock_black_box/tmp_5/train_history.csv
BioNAS/resources/mock_black_box/tmp_6/train_history.csv
BioNAS-0.0.1.dist-info/LICENSE
BioNAS-0.0.1.dist-info/METADATA
BioNAS-0.0.1.dist-info/WHEEL
BioNAS-0.0.1.dist-info/top_level.txt
BioNAS-0.0.1.dist-info/RECORD
