Metadata-Version: 2.1
Name: BioNAS
Version: 0.0.1
Summary: Bioinformatics Neural Architecture Search
Home-page: UNKNOWN
Author: UNKNOWN
Author-email: UNKNOWN
License: UNKNOWN
Download-URL: https://github.com/zj-zhang/BioNAS-pub
Platform: UNKNOWN
Requires-Dist: numpy
Requires-Dist: matplotlib
Requires-Dist: scipy
Requires-Dist: tensorflow (<2.0.0,>=1.9.0)
Requires-Dist: keras (>=2.0.0)
Requires-Dist: seaborn (>=0.9.0)
